pyswitchvox/__init__.py
pyswitchvox/client.py
pyswitchvox-0.0.1.dist-info/DESCRIPTION.rst
pyswitchvox-0.0.1.dist-info/METADATA
pyswitchvox-0.0.1.dist-info/RECORD
pyswitchvox-0.0.1.dist-info/WHEEL
pyswitchvox-0.0.1.dist-info/metadata.json
pyswitchvox-0.0.1.dist-info/top_level.txt
