Metadata-Version: 2.0
Name: pyswitchvox
Version: 0.0.1
Summary: Library for accessing the Switchvox Extend API
Home-page: https://github.com/digium/pyswitchvox
Author: Digium, Inc.
Author-email: mjordan@digium.com
License: BSD 3-Clause License
Platform: UNKNOWN
Classifier: Development Status :: 1 - Planning
Classifier: Intended Audience :: Developers
Classifier: Topic :: Software Development :: Libraries :: Python Modules
Classifier: License :: OSI Approved :: BSD License
Classifier: Operating System :: OS Independent
Classifier: Programming Language :: Python
Requires-Dist: requests (>=2.8.1)
